mcp_server_lark_docx/__init__.py
mcp_server_lark_docx/__main__.py
mcp_server_lark_docx/server.py
mcp_server_lark_docx-0.0.4.dist-info/METADATA
mcp_server_lark_docx-0.0.4.dist-info/WHEEL
mcp_server_lark_docx-0.0.4.dist-info/entry_points.txt
mcp_server_lark_docx-0.0.4.dist-info/licenses/LICENSE
mcp_server_lark_docx-0.0.4.dist-info/RECORD
