Metadata-Version: 2.4
Name: mcp-server-lark-docx
Version: 0.0.4
Summary: A Model Context Protocol server for accessing Lark documents
Author: T0UGH
License: MIT
License-File: LICENSE
Classifier: Development Status :: 4 - Beta
Classifier: Intended Audience :: Developers
Classifier: License :: OSI Approved :: MIT License
Classifier: Programming Language :: Python :: 3
Classifier: Programming Language :: Python :: 3.10
Requires-Python: >=3.10
Requires-Dist: aiohttp>=3.9.0
Requires-Dist: httpx>=0.28.1
Requires-Dist: lark-oapi>=1.0.0
Requires-Dist: mcp[cli]>=1.3.0
